{
  "sentiment_ratio": {
    "positive": 0.5842462443110878,
    "negative": 0.41575375568891215
  },
  "random_positive_comments": [
    "中华人民共和国万岁",
    "陪一根",
    "勿忘国耻",
    "志愿军万岁",
    "中国人民志愿军万岁",
    "敬礼",
    "中国万岁",
    "山西人民向63军敬礼",
    "泪目了",
    "看哭了",
    "祖国万岁",
    "最可爱的人",
    "哭了",
    "山西人民向63军敬礼山西人民向63军敬礼山西人民向63军",
    "喀秋莎",
    "中国人民万岁",
    "中国人民解放军万岁",
    "哭死",
    "中国志愿军万岁",
    "中国共产党万岁"
  ],
  "random_negative_comments": [
    "致敬",
    "致敬英雄",
    "致敬先烈",
    "应该让全社会都组织观看，全民受教育今天生活来之不易",
    "向英雄致敬！！！向英雄致敬！！！向英雄致敬！！！",
    "12.13含泪观看！",
    "致敬最可爱的人",
    "致敬🫡",
    "泪目",
    "向英雄致敬",
    "打卡",
    "致敬先辈",
    "加油",
    "欧豪",
    "铁原阻击战",
    "徐武林又来啦",
    "水淹七军",
    "毛主席万岁",
    "糖呢",
    "好看"
  ]
}